DAY_2/bcd_2_7seg.v
module bcd_to_7seg (bcd,seg);

input [3:0]bcd;
output reg [6:0] seg;

always @(bcd) begin
    case(bcd)

    0: seg = 7'b0000001;
    1: seg = 7'b1001111;
    2: seg = 7'b0010010;
    3: seg = 7'b0000110;
    4: seg = 7'b1001100;
    5: seg = 7'b0100100;
    6: seg = 7'b0100000;
    7: seg = 7'b0001111;
    8: seg = 7'b0000000;
    9: seg = 7'b0000100;

    default : seg = 7'b0000000;


    endcase
end



endmodule

bcd_2_7seg_tb.v
`timescale 1ns/1ps
`include "bcd_2_7seg.v"

module bcd_2_7seg_tb;

    reg  [3:0] bcd;
    wire [6:0] seg;

    
    bcd_to_7seg DUT (
        .bcd(bcd),
        .seg(seg)
    );


    initial begin
        $dumpfile("bcd_2_7seg_tb.vcd");
        $dumpvars(0, bcd_2_7seg_tb);

        $display("Time\tBCD\tSEG");
        $monitor("%0t\t%d\t%b", $time, bcd, seg);

        bcd = 4'd0;
        #5 bcd = 4'd1;
        #5 bcd = 4'd2;
        #5 bcd = 4'd3;
        #5 bcd = 4'd4;
        #5 bcd = 4'd5;
        #5 bcd = 4'd6;
        #5 bcd = 4'd7;
        #5 bcd = 4'd8;
        #5 bcd = 4'd9;
        #50 $finish;
    end

endmodule

DAY_2/bcd_2_7seg_tb.vcd
$date
	Sun Dec 28 10:55:51 2025
$end
$version
	Icarus Verilog
$end
$timescale
	1ps
$end
$scope module bcd_2_7seg_tb $end
$var wire 7 ! seg [6:0] $end
$var reg 4 " bcd [3:0] $end
$scope module DUT $end
$var wire 4 # bcd [3:0] $end
$var reg 7 $ seg [6:0] $end
$upscope $end
$upscope $end
$enddefinitions $end
$comment Show the parameter values. $end
$dumpall
$end
#0
$dumpvars
b1 $
b0 #
b0 "
b1 !
$end
#5000
b1001111 !
b1001111 $
b1 "
b1 #
#10000
b10010 !
b10010 $
b10 "
b10 #
#15000
b110 !
b110 $
b11 "
b11 #
#20000
b1001100 !
b1001100 $
b100 "
b100 #
#25000
b100100 !
b100100 $
b101 "
b101 #
#30000
b100000 !
b100000 $
b110 "
b110 #
#35000
b1111 !
b1111 $
b111 "
b111 #
#40000
b0 !
b0 $
b1000 "
b1000 #
#45000
b100 !
b100 $
b1001 "
b1001 #
