Pr_encoder.v
module priority_encoder(in,code);

input [7:0] in;
output reg [2:0] code;


always @(in) begin

    if(in[0])       code = 3'b000;
    else if (in[1]) code = 3'b001;
    else if (in[2]) code = 3'b010;
    else if (in[3]) code = 3'b011;
    else if (in[4]) code = 3'b100;
    else if (in[5]) code = 3'b101;
    else if (in[6]) code = 3'b110;
    else if (in[7]) code = 3'b111;
    else code = 3'bxxx;

end

endmodule

Pr_encoder_tb.v
`timescale 1ns/1ps
`include "Pr_encoder.v"

module Pr_encoder_tb();

reg [7:0] in;
wire [2:0] code;

priority_encoder DUT (in,code);

initial begin

    $dumpfile("Pr_encoder.vcd");
    $dumpvars(0,Pr_encoder_tb);

    $display("Time\t In Code");
    $monitor("%g\t%b %b", $time, in,code);

    in = 7'd0;
    #5 in = 7'd1;
    #5 in = 7'd2;
    #5 in = 7'd3;
    #5 in = 7'd4;
    #5 in = 7'd5;
    #5 in = 7'd6;
    #5 in = 7'd7;
    #5 in = 7'd8;
    #5 in = 7'd9;

    


end


endmodule

Pr_encoder.vcd
$date
	Sat Dec 27 23:49:19 2025
$end
$version
	Icarus Verilog
$end
$timescale
	1ps
$end
$scope module Pr_encoder_tb $end
$var wire 3 ! code [2:0] $end
$var reg 8 " in [7:0] $end
$scope module DUT $end
$var wire 8 # in [7:0] $end
$var reg 3 $ code [2:0] $end
$upscope $end
$upscope $end
$enddefinitions $end
$comment Show the parameter values. $end
$dumpall
$end
#0
$dumpvars
bx $
b0 #
b0 "
bx !
$end
#5000
b0 !
b0 $
b1 "
b1 #
#10000
b1 !
b1 $
b10 "
b10 #
#15000
b0 !
b0 $
b11 "
b11 #
#20000
b10 !
b10 $
b100 "
b100 #
#25000
b0 !
b0 $
b101 "
b101 #
#30000
b1 !
b1 $
b110 "
b110 #
#35000
b0 !
b0 $
b111 "
b111 #
#40000
b11 !
b11 $
b1000 "
b1000 #
#45000
b0 !
b0 $
b1001 "
b1001 #
