DAY17/fsm_moore.v
module FSM(in,clk,rst,out,change);

input [1:0]in;
input rst;
input clk;
output out;
output [1:0]change;

reg [2:0] tempout;

parameter S0 = 3'b000,S1=3'b001,S2=3'b010,S3=3'b011,S4=3'b100,S5=3'b101,S6=3'b110;
reg [2:0]ps,ns;

always @(posedge clk or posedge rst) begin
    if(rst) ps <= S0; 
    else ps <= ns;
end


//NEXT STATE LOGIC
always @(ps or in) begin
    ns = ps;
    case(ps)

    S0: begin 
        if(in==2'b00) begin 
            ns = S0;
        end
        else if(in==2'b01) begin 
            ns = S1;
        end
        else if(in==2'b10) begin
            ns = S2;
        end
        else begin 
            ns = S0;
        end 
    end

    S1: begin 
        if(in==2'b00) begin 
            ns = S4;
            
        end
        else if(in==2'b01) begin 
            ns = S2;
            
        end
        else if(in==2'b10) begin
            ns = S3;
            
        end
        else begin 
            ns = S0;
        
        end
    end

    S2: begin 
        if(in==2'b00) begin 
            ns = S5;
            
        end
        else if(in==2'b01) begin 
            ns = S3;
            
        end
        else if(in==2'b10) begin
            ns = S6;
           
        end
        else begin 
            ns = S0;
        end

    end



   

    default ns = S0;


    endcase
    

end

//OUTPUT LOGIC
always @(*) begin
    case(ps)
        S0: tempout = 3'b000;
        S1: tempout = 3'b000;
        S2: tempout = 3'b000;
        S3: tempout = 3'b001; // vend
        S4: tempout = 3'b010; // change
        S5: tempout = 3'b100;
        S6: tempout = 3'b011;
        default: tempout = 3'b000;
    endcase
end

assign out = tempout[0];
assign change = tempout[2:1];


endmodule

DAY17/fsm_moore_tb1.v
`timescale 1ns/1ps

module tb_FSM;

    reg clk;
    reg rst;
    reg [1:0] in;

    wire out;
    wire [1:0] change;

    // DUT instantiation
    FSM dut (
        .clk(clk),
        .rst(rst),
        .in(in),
        .out(out),
        .change(change)
    );

    // Clock generation: 10 ns period
    always #5 clk = ~clk;

    initial begin
        // Initial values
        clk = 0;
        rst = 1;
        in  = 2'b00;

        // Dump waveform
        $dumpfile("fsm_moore.vcd");
        $dumpvars(0, tb_FSM);

        // Apply reset
        #12 rst = 0;

        // ----------------------------
        // Case 1: 5 + 10 = 15 (Exact)
        // ----------------------------
        #10 in = 2'b01;   // ₹5
        #10 in = 2'b10;   // ₹10
        #10 in = 2'b00;

        // ----------------------------
        // Case 2: 10 + 10 = 20 (₹5 change)
        // ----------------------------
        #20 in = 2'b10;   // ₹10
        #10 in = 2'b10;   // ₹10
        #10 in = 2'b00;

        // ----------------------------
        // Case 3: 10 + 10 + 5 = 25 (₹10 change)
        // ----------------------------
        #20 in = 2'b10;   // ₹10
        #10 in = 2'b10;   // ₹10
        #10 in = 2'b01;   // ₹5
        #10 in = 2'b00;

        // ----------------------------
        // Reset again
        // ----------------------------
        #20 rst = 1;
        #10 rst = 0;

        #30 $finish;
    end

    // Console monitor
    initial begin
        $monitor("Time=%0t | in=%b | out=%b | change=%b",
                  $time, in, out, change);
    end

endmodule

DAY17/fsm_moore.vcd
$date
	Sun Jan 18 17:23:07 2026
$end
$version
	Icarus Verilog
$end
$timescale
	1ps
$end
$scope module tb_FSM $end
$var wire 1 ! out $end
$var wire 2 " change [1:0] $end
$var reg 1 # clk $end
$var reg 2 $ in [1:0] $end
$var reg 1 % rst $end
$scope module dut $end
$var wire 1 # clk $end
$var wire 2 & in [1:0] $end
$var wire 1 % rst $end
$var wire 1 ! out $end
$var wire 2 ' change [1:0] $end
$var parameter 3 ( S0 $end
$var parameter 3 ) S1 $end
$var parameter 3 * S2 $end
$var parameter 3 + S3 $end
$var parameter 3 , S4 $end
$var parameter 3 - S5 $end
$var parameter 3 . S6 $end
$var reg 3 / ns [2:0] $end
$var reg 3 0 ps [2:0] $end
$var reg 3 1 tempout [2:0] $end
$upscope $end
$upscope $end
$enddefinitions $end
$comment Show the parameter values. $end
$dumpall
b110 .
b101 -
b100 ,
b11 +
b10 *
b1 )
b0 (
$end
#0
$dumpvars
b0 1
b0 0
b0 /
b0 '
b0 &
1%
b0 $
0#
b0 "
0!
$end
#5000
1#
#10000
0#
#12000
0%
#15000
1#
#20000
0#
#22000
b1 /
b1 $
b1 &
#25000
b10 /
b1 0
1#
#30000
0#
#32000
b11 /
b10 $
b10 &
#35000
1!
b1 1
b0 /
b11 0
1#
#40000
0#
#42000
b0 /
b0 $
b0 &
#45000
0!
b0 1
b0 0
1#
#50000
0#
#55000
1#
#60000
0#
#62000
b10 /
b10 $
b10 &
#65000
b110 /
b10 0
1#
#70000
0#
#75000
1!
b1 "
b1 '
b11 1
b0 /
b110 0
1#
#80000
0#
#82000
b0 /
b0 $
b0 &
#85000
0!
b0 "
b0 '
b0 1
b0 0
1#
#90000
0#
#95000
1#
#100000
0#
#102000
b10 /
b10 $
b10 &
#105000
b110 /
b10 0
1#
#110000
0#
#115000
1!
b1 "
b1 '
b11 1
b0 /
b110 0
1#
#120000
0#
#122000
b0 /
b1 $
b1 &
#125000
0!
b0 "
b0 '
b0 1
b1 /
b0 0
1#
#130000
0#
#132000
b0 /
b0 $
b0 &
#135000
1#
#140000
0#
#145000
1#
#150000
0#
#152000
1%
#155000
1#
#160000
0#
#162000
0%
