DAY_11/Shift_Reg.v
module shiftreg(data_out,data_in,S_in,clk,ld,clr,sft);

input S_in,clk,ld,clr,sft;
input [15:0] data_in;
output reg [15:0] data_out;

always @(posedge clk) begin

    if(clr) data_out <= 0;

    else if(ld) data_out <= data_in;

    else if(sft) data_out <= {S_in,data_out[15:1]};


end

endmodule

DAY_11/Shift_reg_Test.v
module shiftreg_tb;

    reg clk,ld,clr,sft,S_in;
    reg [15:0] data_in;
    wire [15:0] data_out;

    shiftreg DUT(data_out,data_in,S_in,clk,ld,clr,sft);
    
    
    
    always #5 clk = ~clk;

    initial begin
        clk = 0;
        ld = 0;
        clr = 0;
        sft = 0;
        S_in = 0;
        data_in = 16'h0000;

        
        #10 clr = 1;
        #10 clr = 0;

        
        #10 ld = 1;
        data_in = 16'hA5A5;
        #10 ld = 0;

        
        #10 sft = 1;
        S_in = 1;
        #10;

        
        S_in = 0;
        #10;

        
        sft = 0;

        
        #20 $finish;
    end

    initial begin
        $monitor("Time=%0t | clr=%b ld=%b sft=%b S_in=%b | data_out=%h",$time, clr, ld, sft, S_in, data_out);
    end

    initial begin
        $dumpfile("shift_reg.vcd");
        $dumpvars(0,shiftreg_tb);
    end

endmodule

DAY_11/shift_reg.vcd
$date
	Tue Jan 06 23:55:44 2026
$end
$version
	Icarus Verilog
$end
$timescale
	1s
$end
$scope module shiftreg_tb $end
$var wire 16 ! data_out [15:0] $end
$var reg 1 " S_in $end
$var reg 1 # clk $end
$var reg 1 $ clr $end
$var reg 16 % data_in [15:0] $end
$var reg 1 & ld $end
$var reg 1 ' sft $end
$scope module DUT $end
$var wire 1 " S_in $end
$var wire 1 # clk $end
$var wire 1 $ clr $end
$var wire 16 ( data_in [15:0] $end
$var wire 1 & ld $end
$var wire 1 ' sft $end
$var reg 16 ) data_out [15:0] $end
$upscope $end
$upscope $end
$enddefinitions $end
$comment Show the parameter values. $end
$dumpall
$end
#0
$dumpvars
bx )
b0 (
0'
0&
b0 %
0$
0#
0"
bx !
$end
#5
1#
#10
0#
1$
#15
b0 !
b0 )
1#
#20
0#
0$
#25
1#
#30
0#
b1010010110100101 %
b1010010110100101 (
1&
#35
b1010010110100101 !
b1010010110100101 )
1#
#40
0#
0&
#45
1#
#50
0#
1"
1'
#55
b1101001011010010 !
b1101001011010010 )
1#
#60
0#
0"
#65
b110100101101001 !
b110100101101001 )
1#
#70
0#
0'
