DAY12/Control_Path.v
module controller(ldA,ldB,ldP,clrP,decB,done,clk,eqz,start);

input clk,eqz,start;
output reg ldA,ldB,ldP,clrP,decB,done;

parameter S0=3'b000,S1=3'b001,S2=3'b010,S3=3'b011,S4=3'b100;

reg[2:0] state;

always@(posedge clk)
begin

    case(state)

    S0: if(start) state <= S1;
    S1: state <= S2;
    S2: state <= S3;
    S3: #2 if(eqz) state <= S4;
    S4: state <=S4;
    default : state <= S0;



    endcase




end

always @(state) begin
    case(state)

        S0: begin 
            #1 ldA = 0;ldB = 0;ldP = 0;clrP = 0;decB = 0;
            
            end

        S1: begin 
            #1 ldA = 1;
        end

        S2: begin 
            #1 ldA = 0; ldB = 1; clrP = 1;
        end

        S3: begin 
            ldB = 0;ldP = 1;clrP = 0;decB=1; 
        end

        S4: begin 
            #1 done = 1; ldB = 0; ldP = 0;decB=0;
        end

        default: begin #1 ldA = 0;ldB = 0; ldP = 0; clrP = 0; decB = 0;
        end


    endcase
end

endmodule

DAY12/EQZ.v
module EQZ(eqz,data);
input [15:0] data;
output eqz;


assign eqz = (data == 0);

endmodule

DAY12/ADD.v
module ADD(out,in1,in2);

input [15:0] in1,in2;
output reg [15:0] out;

always@(*) out = in1+in2;



endmodule

DAY12/COUNTER.V
module counter(dout,din,ld,dec,clk);


input [15:0] din;
input ld,dec,clk;


output reg [15:0] dout;

always@(posedge clk)begin 
if(ld) dout<=din;
else if(dec) dout <= dout -1;
end

endmodule

DAY12/PIPO2.v
module PIPO2(dout,din,ld,clk,clr);

input [15:0]din;
input clk,ld,clr;


output reg[15:0]dout;

always @(posedge clk) begin
    if(clr) dout <= 16'b0;
    else if(ld) dout <= din;
end


endmodule

DAY12/PIPO1.v
module PIPO1(dout,din,ld,clk);

input [15:0]din;
input clk,ld;


output reg[15:0]dout;

always @(posedge clk) begin
    if(ld) dout <= din;
end


endmodule

DAY12/Data_Path.v
module MUL_ADD(eqz,ldA,ldB,ldP,clrP,decB,data_in,clk,mul_out);


input ldA,ldB,ldP,clrP,decB,clk;
output eqz;
input [15:0] data_in;
output reg [15:0] mul_out;

wire [15:0] X,Y,Z,Bout,Bus;


PIPO1 P1(X,Bus,ldA,clk);
PIPO2 P2(Y,Z,ldP,clrP,clk);
counter C1(Bout,Bus,ldB,decB,clk);
ADD A1(Z,X,Y);
EQZ compare(eqz,Bout);

always@(*)
begin 

    mul_out <= Y;
end



endmodule

DAY12/Test.v
module MUL_ADD_TEST();

reg[15:0] data_in;
reg clk,start;
wire done;
wire [15:0] out;


MUL_ADD DUT(eqz,ldA,ldB,ldP,clrP,decB,data_in,clk,out);

controller DUT1(ldA,ldB,ldP,clrP,decB,done,clk,eqz,start);

initial begin
    clk = 1'b0;
    #3 start = 1'b1;
    #500 $finish;
end

always #5 clk = ~clk;

initial begin
    #17 data_in = 17;
    #10 data_in = 5;
end

initial
begin
    $monitor($time,"%d %b",out,done);
    $dumpfile("mul.vcd");
    $dumpvars(0,MUL_ADD_TEST);


end

endmodule

DAY12/mul.vcd
$date
	Wed Jan 07 23:50:46 2026
$end
$version
	Icarus Verilog
$end
$timescale
	1s
$end
$scope module MUL_ADD_TEST $end
$var wire 16 ! out [15:0] $end
$var wire 1 " ldP $end
$var wire 1 # ldB $end
$var wire 1 $ ldA $end
$var wire 1 % eqz $end
$var wire 1 & done $end
$var wire 1 ' decB $end
$var wire 1 ( clrP $end
$var reg 1 ) clk $end
$var reg 16 * data_in [15:0] $end
$var reg 1 + start $end
$scope module DUT $end
$var wire 16 , Bus [15:0] $end
$var wire 1 ) clk $end
$var wire 16 - data_in [15:0] $end
$var wire 1 " ldP $end
$var wire 1 # ldB $end
$var wire 1 $ ldA $end
$var wire 1 % eqz $end
$var wire 1 ' decB $end
$var wire 1 ( clrP $end
$var wire 16 . Z [15:0] $end
$var wire 16 / Y [15:0] $end
$var wire 16 0 X [15:0] $end
$var wire 16 1 Bout [15:0] $end
$var reg 16 2 mul_out [15:0] $end
$scope module A1 $end
$var wire 16 3 in2 [15:0] $end
$var wire 16 4 in1 [15:0] $end
$var reg 16 5 out [15:0] $end
$upscope $end
$scope module C1 $end
$var wire 1 ) clk $end
$var wire 16 6 din [15:0] $end
$var wire 1 # ld $end
$var wire 1 ' dec $end
$var reg 16 7 dout [15:0] $end
$upscope $end
$scope module P1 $end
$var wire 1 ) clk $end
$var wire 16 8 din [15:0] $end
$var wire 1 $ ld $end
$var reg 16 9 dout [15:0] $end
$upscope $end
$scope module P2 $end
$var wire 1 ) clr $end
$var wire 16 : din [15:0] $end
$var wire 1 " ld $end
$var wire 1 ( clk $end
$var reg 16 ; dout [15:0] $end
$upscope $end
$scope module compare $end
$var wire 16 < data [15:0] $end
$var wire 1 % eqz $end
$upscope $end
$upscope $end
$scope module DUT1 $end
$var wire 1 ) clk $end
$var wire 1 % eqz $end
$var wire 1 + start $end
$var parameter 3 = S0 $end
$var parameter 3 > S1 $end
$var parameter 3 ? S2 $end
$var parameter 3 @ S3 $end
$var parameter 3 A S4 $end
$var reg 1 ( clrP $end
$var reg 1 ' decB $end
$var reg 1 & done $end
$var reg 1 $ ldA $end
$var reg 1 # ldB $end
$var reg 1 " ldP $end
$var reg 3 B state [2:0] $end
$upscope $end
$upscope $end
$enddefinitions $end
$comment Show the parameter values. $end
$dumpall
b100 A
b11 @
b10 ?
b1 >
b0 =
$end
#0
$dumpvars
bx B
bx <
bx ;
bx :
bx 9
bz 8
bx 7
bz 6
bx 5
bx 4
bx 3
bx 2
bx 1
bx 0
bx /
bx .
bx -
bz ,
x+
bx *
0)
x(
x'
x&
x%
x$
x#
x"
bx !
$end
#3
1+
#5
b0 B
1)
#6
0'
0(
0"
0#
0$
#10
0)
#15
b1 B
1)
#16
1$
#17
b10001 *
b10001 -
#20
0)
#25
bz 0
bz 4
bz 9
b10 B
1)
#26
b0 !
b0 2
b0 /
b0 3
b0 ;
1(
1#
0$
#27
b101 *
b101 -
#30
0)
#35
1'
0(
1"
0#
b11 B
bz 1
bz 7
bz <
1)
#40
0)
#45
bx 1
bx 7
bx <
1)
